grnvae/__init__.py
grnvae/data.py
grnvae/evaluate.py
grnvae/logger.py
grnvae/models.py
grnvae/runner.py
grnvae/.ipynb_checkpoints/__init__-checkpoint.py
grnvae/.ipynb_checkpoints/data-checkpoint.py
grnvae/.ipynb_checkpoints/evaluate-checkpoint.py
grnvae/.ipynb_checkpoints/logger-checkpoint.py
grnvae/.ipynb_checkpoints/models-checkpoint.py
grnvae/.ipynb_checkpoints/runner-checkpoint.py
grnvae-0.0.3.dist-info/LICENSE
grnvae-0.0.3.dist-info/WHEEL
grnvae-0.0.3.dist-info/METADATA
grnvae-0.0.3.dist-info/RECORD
